single_body_thermal_equil/__init__.py
single_body_thermal_equil/single_body_thermal_equil.py
single_body_thermal_equil/test_equilibrium_temperature.py
single_body_thermal_equil-0.0.0.dist-info/LICENSE.md
single_body_thermal_equil-0.0.0.dist-info/METADATA
single_body_thermal_equil-0.0.0.dist-info/WHEEL
single_body_thermal_equil-0.0.0.dist-info/top_level.txt
single_body_thermal_equil-0.0.0.dist-info/RECORD
