Metadata-Version: 2.1
Name: single-body-thermal-equil
Version: 0.0.0
Summary: Find the equilibirium temperature of a body with multiple conductive and radiative boundaries
Home-page: https://github.com/mvernacc/single-body-thermal-equil
Author: Matthew Vernacchia
Author-email: mvernacc@mit.edu
License: MIT License
Requires-Dist: numpy
Requires-Dist: scipy
Provides-Extra: test
Requires-Dist: pytest ; extra == 'test'
Requires-Dist: coverage ; extra == 'test'
Requires-Dist: pytest-cov ; extra == 'test'
Requires-Dist: numpy ; extra == 'test'
Requires-Dist: scipy ; extra == 'test'
